LICENSE
README.md
setup.py
hydroanalysis/__init__.py
hydroanalysis/meteo_indexes.py
hydroanalysis/metrics.py
hydroanalysis/streamflow_signatures.py
hydroanalysis/utils.py
hydroanalysis.egg-info/PKG-INFO
hydroanalysis.egg-info/SOURCES.txt
hydroanalysis.egg-info/dependency_links.txt
hydroanalysis.egg-info/requires.txt
hydroanalysis.egg-info/top_level.txt