Metadata-Version: 2.1
Name: hydroanalysis
Version: 1.0.1
Summary: Framework for calculating hydrological indices
Home-page: https://hydroanalysis.readthedocs.io/en/latest/
Author: Marco Dal Molin
Author-email: marco.dalmolin.1991@gmail.com
License: LGPL
Platform: UNKNOWN
Classifier: Development Status :: 2 - Pre-Alpha
Classifier: Topic :: Scientific/Engineering :: Hydrology
License-File: LICENSE
